README.rst
setup.py
rwdb/__init__.py
rwdb.egg-info/PKG-INFO
rwdb.egg-info/SOURCES.txt
rwdb.egg-info/dependency_links.txt
rwdb.egg-info/requires.txt
rwdb.egg-info/top_level.txt
test/test_rwdb.py