Metadata-Version: 1.0
Name: rwdb
Version: 0.0.4
Summary: tornado based webframework
Home-page: https://github.com/FlorianLudwig/rwdb
Author: Florian Ludwig
Author-email: vierzigundzwei@gmail.com
License: UNKNOWN
Platform: UNKNOWN
